Workbook
Name Slicer_Months__Order_Date: #N/A
Name Slicer_Sources: #N/A
Name Slicer_Years__Order_Date: #N/A

Sheet Pivot
B4: Sum of Revenue | C4: Sum of Expenses | D4: Sum of Quantity | E4: Sum of Profit | F4: Count of Order_ID | G4: Average of Expense_Ratio_% | H4: Average of Profit_Margin_% | I4: Average of Return_Rate_% | J4: Average of Discount_%
B5: 401664.6 | C5: 257496.81 | D5: 2103 | E5: 144167.79 | F5: 500 | G5: 0.6444222 | H5: 0.3555782 | I5: 0.0478006 | J5: 0.05364
C8: Column Labels
C9: 2025 | H9: 2024 | M9: Total Sum of Revenue | N9: Total Sum of Expenses | O9: Total Sum of Quantity | P9: Total Sum of Profit | Q9: Total Count of Order_ID
B10: Row Labels | C10: Sum of Revenue | D10: Sum of Expenses | E10: Sum of Quantity | F10: Sum of Profit | G10: Count of Order_ID | H10: Sum of Revenue | I10: Sum of Expenses | J10: Sum of Quantity | K10: Sum of Profit | L10: Count of Order_ID
B11: Jan | C11: 13460.4 | D11: 8422.65 | E11: 84 | F11: 5037.75 | G11: 25 | H11: 18415.75 | I11: 12809.84 | J11: 88 | K11: 5605.91 | L11: 26 | M11: 31876.15 | N11: 21232.49 | O11: 172 | P11: 10643.66 | Q11: 51
B12: Feb | C12: 21868 | D12: 12701.69 | E12: 93 | F12: 9166.31 | G12: 27 | H12: 24586.8 | I12: 14518.01 | J12: 106 | K12: 10068.79 | L12: 26 | M12: 46454.8 | N12: 27219.7 | O12: 199 | P12: 19235.1 | Q12: 53
B13: Mar | C13: 14333.7 | D13: 8719.55 | E13: 59 | F13: 5614.15 | G13: 19 | H13: 10873 | I13: 6755.89 | J13: 99 | K13: 4117.11 | L13: 24 | M13: 25206.7 | N13: 15475.44 | O13: 158 | P13: 9731.26 | Q13: 43
B14: Apr | C14: 12644.9 | D14: 7314.99 | E14: 62 | F14: 5329.91 | G14: 20 | H14: 19689.05 | I14: 10632.34 | J14: 93 | K14: 9056.71 | L14: 20 | M14: 32333.95 | N14: 17947.33 | O14: 155 | P14: 14386.62 | Q14: 40
B15: May | C15: 15540.4 | D15: 10348.08 | E15: 89 | F15: 5192.32 | G15: 16 | H15: 13977.7 | I15: 9440.95 | J15: 79 | K15: 4536.75 | L15: 21 | M15: 29518.1 | N15: 19789.03 | O15: 168 | P15: 9729.07 | Q15: 37
B16: Jun | C16: 7325.6 | D16: 4342.19 | E16: 42 | F16: 2983.41 | G16: 11 | H16: 16213 | I16: 9461.8 | J16: 83 | K16: 6751.2 | L16: 21 | M16: 23538.6 | N16: 13803.99 | O16: 125 | P16: 9734.61 | Q16: 32
B17: Jul | C17: 25464.95 | D17: 16956.55 | E17: 101 | F17: 8508.4 | G17: 22 | H17: 17043.5 | I17: 10952.52 | J17: 94 | K17: 6090.98 | L17: 22 | M17: 42508.45 | N17: 27909.07 | O17: 195 | P17: 14599.38 | Q17: 44
B18: Aug | C18: 18369.3 | D18: 12636.02 | E18: 101 | F18: 5733.28 | G18: 19 | H18: 17356.8 | I18: 11629.96 | J18: 101 | K18: 5726.84 | L18: 25 | M18: 35726.1 | N18: 24265.98 | O18: 202 | P18: 11460.12 | Q18: 44
B19: Sep | C19: 15871.9 | D19: 8909.84 | E19: 82 | F19: 6962.06 | G19: 19 | H19: 9733 | I19: 5406.44 | J19: 36 | K19: 4326.56 | L19: 10 | M19: 25604.9 | N19: 14316.28 | O19: 118 | P19: 11288.62 | Q19: 29
B20: Oct | C20: 12267.4 | D20: 8504.58 | E20: 115 | F20: 3762.82 | G20: 24 | H20: 10162.65 | I20: 7280.39 | J20: 85 | K20: 2882.26 | L20: 21 | M20: 22430.05 | N20: 15784.97 | O20: 200 | P20: 6645.08 | Q20: 45
B21: Nov | C21: 29592.4 | D21: 19748 | E21: 113 | F21: 9844.4 | G21: 21 | H21: 14026.55 | I21: 8692.33 | J21: 76 | K21: 5334.22 | L21: 16 | M21: 43618.95 | N21: 28440.33 | O21: 189 | P21: 15178.62 | Q21: 37
B22: Dec | C22: 26586.2 | D22: 19349.24 | E22: 111 | F22: 7236.96 | G22: 23 | H22: 16261.65 | I22: 11962.96 | J22: 111 | K22: 4298.69 | L22: 22 | M22: 42847.85 | N22: 31312.2 | O22: 222 | P22: 11535.65 | Q22: 45
B23: Grand Total | C23: 213325.15 | D23: 137953.38 | E23: 1052 | F23: 75371.77 | G23: 246 | H23: 188339.45 | I23: 119543.43 | J23: 1051 | K23: 68796.02 | L23: 254 | M23: 401664.6 | N23: 257496.81 | O23: 2103 | P23: 144167.79 | Q23: 500
B27: Row Labels | C27: Sum of Revenue | D27: Sum of Profit | E27: Sum of Sales_Target | F27: Sum of Expenses | G27: Sum of Quantity
B28: Jan | C28: 31876.15 | D28: 10643.66 | E28: 32308 | F28: 21232.49 | G28: 172
B29: Feb | C29: 46454.8 | D29: 19235.1 | E29: 43973 | F29: 27219.7 | G29: 199
B30: Mar | C30: 25206.7 | D30: 9731.26 | E30: 27964 | F30: 15475.44 | G30: 158
B31: Apr | C31: 32333.95 | D31: 14386.62 | E31: 31226 | F31: 17947.33 | G31: 155
B32: May | C32: 29518.1 | D32: 9729.07 | E32: 29988 | F32: 19789.03 | G32: 168
B33: Jun | C33: 23538.6 | D33: 9734.61 | E33: 22413 | F33: 13803.99 | G33: 125
B34: Jul | C34: 42508.45 | D34: 14599.38 | E34: 47522 | F34: 27909.07 | G34: 195
B35: Aug | C35: 35726.1 | D35: 11460.12 | E35: 34529 | F35: 24265.98 | G35: 202
B36: Sep | C36: 25604.9 | D36: 11288.62 | E36: 29035 | F36: 14316.28 | G36: 118
B37: Oct | C37: 22430.05 | D37: 6645.08 | E37: 19967 | F37: 15784.97 | G37: 200
B38: Nov | C38: 43618.95 | D38: 15178.62 | E38: 44484 | F38: 28440.33 | G38: 189
B39: Dec | C39: 42847.85 | D39: 11535.65 | E39: 38871 | F39: 31312.2 | G39: 222
B40: Grand Total | C40: 401664.6 | D40: 144167.79 | E40: 402280 | F40: 257496.81 | G40: 2103
B44: Row Labels | C44: Sum of Revenue | D44: Sum of Profit | E44: Sum of Sales_Target | F44: Sum of Expenses | G44: Sum of Quantity
B45: Jan | C45: 31876.15 | D45: 10643.66 | E45: 32308 | F45: 21232.49 | G45: 172
B46: Feb | C46: 46454.8 | D46: 19235.1 | E46: 43973 | F46: 27219.7 | G46: 199
B47: Mar | C47: 25206.7 | D47: 9731.26 | E47: 27964 | F47: 15475.44 | G47: 158
B48: Apr | C48: 32333.95 | D48: 14386.62 | E48: 31226 | F48: 17947.33 | G48: 155
B49: May | C49: 29518.1 | D49: 9729.07 | E49: 29988 | F49: 19789.03 | G49: 168
B50: Jun | C50: 23538.6 | D50: 9734.61 | E50: 22413 | F50: 13803.99 | G50: 125
B51: Jul | C51: 42508.45 | D51: 14599.38 | E51: 47522 | F51: 27909.07 | G51: 195
B52: Aug | C52: 35726.1 | D52: 11460.12 | E52: 34529 | F52: 24265.98 | G52: 202
B53: Sep | C53: 25604.9 | D53: 11288.62 | E53: 29035 | F53: 14316.28 | G53: 118
B54: Oct | C54: 22430.05 | D54: 6645.08 | E54: 19967 | F54: 15784.97 | G54: 200
B55: Nov | C55: 43618.95 | D55: 15178.62 | E55: 44484 | F55: 28440.33 | G55: 189
B56: Dec | C56: 42847.85 | D56: 11535.65 | E56: 38871 | F56: 31312.2 | G56: 222
B57: Grand Total | C57: 401664.6 | D57: 144167.79 | E57: 402280 | F57: 257496.81 | G57: 2103
B60: Row Labels | C60: Sum of Revenue
B61: Accessories | C61: 89198.9
B62: Appliances | C62: 55714.75
B63: Furniture | C63: 64075.95
B64: Office Supplies | C64: 88250.5
B65: Technology | C65: 104424.5
B66: Grand Total | C66: 401664.6
B69: Row Labels | C69: Sum of Revenue
B70: Consumer | C70: 79123.5
B71: Corporate | C71: 85563.2
B72: Enterprise | C72: 75437.7
B73: Retail | C73: 161540.2
B74: Grand Total | C74: 401664.6
B78: Row Labels | C78: Sum of Revenue
B79: Midwest | C79: 73286.7
B80: Northeast | C80: 97010.2
B81: South | C81: 100937.25
B82: West | C82: 130430.45
B83: Grand Total | C83: 401664.6
B87: Row Labels
B88: Midwest
B89: Northeast
B90: South
B91: West
B92: Grand Total
B96: Sum of Revenue | C96: Column Labels
B97: Row Labels | C97: 2025 | D97: 2024 | E97: Grand Total
B98: New | C98: 73854.7 | D98: 80446.15 | E98: 154300.85
B99: Returning | C99: 139470.45 | D99: 107893.3 | E99: 247363.75
B100: Grand Total | C100: 213325.15 | D100: 188339.45 | E100: 401664.6
B104: Row Labels | C104: Sum of Revenue
B105: New | C105: 154300.85
B106: Returning | C106: 247363.75
B107: Grand Total | C107: 401664.6
B110: Row Labels | C110: Sum of Revenue
B111: Accessories | C111: 89198.9
B112: Appliances | C112: 55714.75
B113: Furniture | C113: 64075.95
B114: Office Supplies | C114: 88250.5
B115: Technology | C115: 104424.5
B116: Grand Total | C116: 401664.6
B119: Row Labels | C119: Sum of Revenue
B120: Express | C120: 96898.1
B121: Standard | C121: 304766.5
B122: Grand Total | C122: 401664.6

Sheet Processing
B1: Total Revenue | C1: Total Expenses | D1: Total Quantity | E1: Total Profit | F1: Avg Order Value
B2: =GETPIVOTDATA("Sum of Revenue",Pivot!$B$4) -> 401664.6 | C2: =GETPIVOTDATA("Sum of Expenses",Pivot!$B$4) -> 257496.81 | D2: =GETPIVOTDATA("Sum of Quantity",Pivot!$B$4) -> 2103 | E2: =GETPIVOTDATA("Sum of Profit",Pivot!$B$4) -> 144167.79 | F2: =B2/GETPIVOTDATA("Count of Order_ID",Pivot!$B$4) -> 803.3292
B4: Renvenue 2024 | C4: Expenses 2024 | D4: Quantity 2024 | E4: Profit 2024
B5: =GETPIVOTDATA("Sum of Revenue",Pivot!$B$8,"Years (Order_Date)",2024) -> 188339.45 | C5: =GETPIVOTDATA("Sum of Expenses",Pivot!$B$8,"Years (Order_Date)",2024) -> 119543.43 | D5: =GETPIVOTDATA("Sum of Quantity",Pivot!$B$8,"Years (Order_Date)",2024) -> 1051 | E5: =GETPIVOTDATA("Sum of Profit",Pivot!$B$8,"Years (Order_Date)",2024) -> 68796.02
B7: Renvenue 2025 | C7: Expenses 2025 | D7: Quantity 2025 | E7: Profit 2025 | G7: [>=1000000]$0.00,,"M";[>=1000]$0.00,"K";0.00
B8: =GETPIVOTDATA("Sum of Revenue",Pivot!$B$8,"Years (Order_Date)",2025) -> 213325.15 | C8: =GETPIVOTDATA("Sum of Expenses",Pivot!$B$8,"Years (Order_Date)",2025) -> 137953.38 | D8: =GETPIVOTDATA("Sum of Quantity",Pivot!$B$8,"Years (Order_Date)",2025) -> 1052 | E8: =GETPIVOTDATA("Sum of Profit",Pivot!$B$8,"Years (Order_Date)",2025) -> 75371.77
B10: YoY Growth | C10: YoY Growth | D10: YoY Growth | E10: YoY Growth
B11: =(B8-B5)/B5 -> 0.13266313 | C11: =(C8-C5)/C5 -> 0.15400219 | D11: =(D8-D5)/D5 -> 0.00095147479 | E11: =(E8-E5)/E5 -> 0.095583291
A13: Positive | B13: =IF(B11>0,B11,"") -> 0.13266313 | C13: =IF(C11>0,C11,"") -> 0.15400219 | D13: =IF(D11>0,D11,"") -> 0.00095147479 | E13: =IF(E11>0,E11,"") -> 0.095583291
A14: Negative | B14: =IF(B11<0,B11,"") | C14: =IF(C11<0,C11,"") | D14: =IF(D11<0,D11,"") | E14: =IF(E11<0,E11,"")
D16: =MAX(B18:B29)*5% -> 961.755
A17: Monthly Profit Trends | B17: Profit | C17: Cursor P | D17: Cusor Indent
A18: Jan | B18: =GETPIVOTDATA("Sum of Profit",Pivot!$B$44,"Months (Order_Date)",A18) -> 10643.66 | C18: =IFERROR(GETPIVOTDATA("Sum of Profit",Pivot!$B$27,"Months (Order_Date)",A18),NA()) -> 10643.66 | D18: =IF(ISNUMBER(C18),$D$16,NA()) -> 961.755
A19: Feb | B19: =GETPIVOTDATA("Sum of Profit",Pivot!$B$44,"Months (Order_Date)",A19) -> 19235.1 | C19: =IFERROR(GETPIVOTDATA("Sum of Profit",Pivot!$B$27,"Months (Order_Date)",A19),NA()) -> 19235.1 | D19: =IF(ISNUMBER(C19),$D$16,NA()) -> 961.755
A20: Mar | B20: =GETPIVOTDATA("Sum of Profit",Pivot!$B$44,"Months (Order_Date)",A20) -> 9731.26 | C20: =IFERROR(GETPIVOTDATA("Sum of Profit",Pivot!$B$27,"Months (Order_Date)",A20),NA()) -> 9731.26 | D20: =IF(ISNUMBER(C20),$D$16,NA()) -> 961.755
A21: Apr | B21: =GETPIVOTDATA("Sum of Profit",Pivot!$B$44,"Months (Order_Date)",A21) -> 14386.62 | C21: =IFERROR(GETPIVOTDATA("Sum of Profit",Pivot!$B$27,"Months (Order_Date)",A21),NA()) -> 14386.62 | D21: =IF(ISNUMBER(C21),$D$16,NA()) -> 961.755
A22: May | B22: =GETPIVOTDATA("Sum of Profit",Pivot!$B$44,"Months (Order_Date)",A22) -> 9729.07 | C22: =IFERROR(GETPIVOTDATA("Sum of Profit",Pivot!$B$27,"Months (Order_Date)",A22),NA()) -> 9729.07 | D22: =IF(ISNUMBER(C22),$D$16,NA()) -> 961.755
A23: Jun | B23: =GETPIVOTDATA("Sum of Profit",Pivot!$B$44,"Months (Order_Date)",A23) -> 9734.61 | C23: =IFERROR(GETPIVOTDATA("Sum of Profit",Pivot!$B$27,"Months (Order_Date)",A23),NA()) -> 9734.61 | D23: =IF(ISNUMBER(C23),$D$16,NA()) -> 961.755
A24: Jul | B24: =GETPIVOTDATA("Sum of Profit",Pivot!$B$44,"Months (Order_Date)",A24) -> 14599.38 | C24: =IFERROR(GETPIVOTDATA("Sum of Profit",Pivot!$B$27,"Months (Order_Date)",A24),NA()) -> 14599.38 | D24: =IF(ISNUMBER(C24),$D$16,NA()) -> 961.755
A25: Aug | B25: =GETPIVOTDATA("Sum of Profit",Pivot!$B$44,"Months (Order_Date)",A25) -> 11460.12 | C25: =IFERROR(GETPIVOTDATA("Sum of Profit",Pivot!$B$27,"Months (Order_Date)",A25),NA()) -> 11460.12 | D25: =IF(ISNUMBER(C25),$D$16,NA()) -> 961.755
A26: Sep | B26: =GETPIVOTDATA("Sum of Profit",Pivot!$B$44,"Months (Order_Date)",A26) -> 11288.62 | C26: =IFERROR(GETPIVOTDATA("Sum of Profit",Pivot!$B$27,"Months (Order_Date)",A26),NA()) -> 11288.62 | D26: =IF(ISNUMBER(C26),$D$16,NA()) -> 961.755
A27: Oct | B27: =GETPIVOTDATA("Sum of Profit",Pivot!$B$44,"Months (Order_Date)",A27) -> 6645.08 | C27: =IFERROR(GETPIVOTDATA("Sum of Profit",Pivot!$B$27,"Months (Order_Date)",A27),NA()) -> 6645.08 | D27: =IF(ISNUMBER(C27),$D$16,NA()) -> 961.755
A28: Nov | B28: =GETPIVOTDATA("Sum of Profit",Pivot!$B$44,"Months (Order_Date)",A28) -> 15178.62 | C28: =IFERROR(GETPIVOTDATA("Sum of Profit",Pivot!$B$27,"Months (Order_Date)",A28),NA()) -> 15178.62 | D28: =IF(ISNUMBER(C28),$D$16,NA()) -> 961.755
A29: Dec | B29: =GETPIVOTDATA("Sum of Profit",Pivot!$B$44,"Months (Order_Date)",A29) -> 11535.65 | C29: =IFERROR(GETPIVOTDATA("Sum of Profit",Pivot!$B$27,"Months (Order_Date)",A29),NA()) -> 11535.65 | D29: =IF(ISNUMBER(C29),$D$16,NA()) -> 961.755
C30: =SUMIF(C18:C29,">0") -> 144167.79
A32: Monthly Revenue Trends | D32: FALSE
A33: Month | B33: Sales | C33: Sales Plan | D33: Line Plan | E33: padding | F33: Cursor | G33: Marker
A34: JAN | B34: =GETPIVOTDATA("Sum of Revenue",Pivot!$B$44,"Months (Order_Date)",A34) -> 31876.15 | C34: =GETPIVOTDATA("Sum of Sales_Target",Pivot!$B$44,"Months (Order_Date)",A34) -> 32308 | D34: =IF($D$32,IFERROR(GETPIVOTDATA("Sum of Sales_Target",Pivot!$B$44,"Months (Order_Date)",A34),NA()),NA()) -> #N/A | E34: -3000 | F34: =IFERROR(GETPIVOTDATA("Sum of Revenue",Pivot!$B$27,"Months (Order_Date)",A34)+MAX($B$34:$B$45)*$F$46,NA()) -> 38844.37 | G34: =IFERROR(GETPIVOTDATA("Sum of Revenue",Pivot!$B$27,"Months (Order_Date)",A34),NA()) -> 31876.15 | H34: Switch
A35: FEB | B35: =GETPIVOTDATA("Sum of Revenue",Pivot!$B$44,"Months (Order_Date)",A35) -> 46454.8 | C35: =GETPIVOTDATA("Sum of Sales_Target",Pivot!$B$44,"Months (Order_Date)",A35) -> 43973 | D35: =IF($D$32,IFERROR(GETPIVOTDATA("Sum of Sales_Target",Pivot!$B$44,"Months (Order_Date)",A35),NA()),NA()) -> #N/A | E35: -3000 | F35: =IFERROR(GETPIVOTDATA("Sum of Revenue",Pivot!$B$27,"Months (Order_Date)",A35)+MAX($B$34:$B$45)*$F$46,NA()) -> 53423.02 | G35: =IFERROR(GETPIVOTDATA("Sum of Revenue",Pivot!$B$27,"Months (Order_Date)",A35),NA()) -> 46454.8 | H35: =IF(D32,0,1) -> 1 | I35: =IF(D32,1,0)
A36: MAR | B36: =GETPIVOTDATA("Sum of Revenue",Pivot!$B$44,"Months (Order_Date)",A36) -> 25206.7 | C36: =GETPIVOTDATA("Sum of Sales_Target",Pivot!$B$44,"Months (Order_Date)",A36) -> 27964 | D36: =IF($D$32,IFERROR(GETPIVOTDATA("Sum of Sales_Target",Pivot!$B$44,"Months (Order_Date)",A36),NA()),NA()) -> #N/A | E36: -3000 | F36: =IFERROR(GETPIVOTDATA("Sum of Revenue",Pivot!$B$27,"Months (Order_Date)",A36)+MAX($B$34:$B$45)*$F$46,NA()) -> 32174.92 | G36: =IFERROR(GETPIVOTDATA("Sum of Revenue",Pivot!$B$27,"Months (Order_Date)",A36),NA()) -> 25206.7 | H36: =IF(D32,1,0) -> 0
A37: APR | B37: =GETPIVOTDATA("Sum of Revenue",Pivot!$B$44,"Months (Order_Date)",A37) -> 32333.95 | C37: =GETPIVOTDATA("Sum of Sales_Target",Pivot!$B$44,"Months (Order_Date)",A37) -> 31226 | D37: =IF($D$32,IFERROR(GETPIVOTDATA("Sum of Sales_Target",Pivot!$B$44,"Months (Order_Date)",A37),NA()),NA()) -> #N/A | E37: -3000 | F37: =IFERROR(GETPIVOTDATA("Sum of Revenue",Pivot!$B$27,"Months (Order_Date)",A37)+MAX($B$34:$B$45)*$F$46,NA()) -> 39302.17 | G37: =IFERROR(GETPIVOTDATA("Sum of Revenue",Pivot!$B$27,"Months (Order_Date)",A37),NA()) -> 32333.95
A38: MAY | B38: =GETPIVOTDATA("Sum of Revenue",Pivot!$B$44,"Months (Order_Date)",A38) -> 29518.1 | C38: =GETPIVOTDATA("Sum of Sales_Target",Pivot!$B$44,"Months (Order_Date)",A38) -> 29988 | D38: =IF($D$32,IFERROR(GETPIVOTDATA("Sum of Sales_Target",Pivot!$B$44,"Months (Order_Date)",A38),NA()),NA()) -> #N/A | E38: -3000 | F38: =IFERROR(GETPIVOTDATA("Sum of Revenue",Pivot!$B$27,"Months (Order_Date)",A38)+MAX($B$34:$B$45)*$F$46,NA()) -> 36486.32 | G38: =IFERROR(GETPIVOTDATA("Sum of Revenue",Pivot!$B$27,"Months (Order_Date)",A38),NA()) -> 29518.1
A39: JUN | B39: =GETPIVOTDATA("Sum of Revenue",Pivot!$B$44,"Months (Order_Date)",A39) -> 23538.6 | C39: =GETPIVOTDATA("Sum of Sales_Target",Pivot!$B$44,"Months (Order_Date)",A39) -> 22413 | D39: =IF($D$32,IFERROR(GETPIVOTDATA("Sum of Sales_Target",Pivot!$B$44,"Months (Order_Date)",A39),NA()),NA()) -> #N/A | E39: -3000 | F39: =IFERROR(GETPIVOTDATA("Sum of Revenue",Pivot!$B$27,"Months (Order_Date)",A39)+MAX($B$34:$B$45)*$F$46,NA()) -> 30506.82 | G39: =IFERROR(GETPIVOTDATA("Sum of Revenue",Pivot!$B$27,"Months (Order_Date)",A39),NA()) -> 23538.6
A40: JUL | B40: =GETPIVOTDATA("Sum of Revenue",Pivot!$B$44,"Months (Order_Date)",A40) -> 42508.45 | C40: =GETPIVOTDATA("Sum of Sales_Target",Pivot!$B$44,"Months (Order_Date)",A40) -> 47522 | D40: =IF($D$32,IFERROR(GETPIVOTDATA("Sum of Sales_Target",Pivot!$B$44,"Months (Order_Date)",A40),NA()),NA()) -> #N/A | E40: -3000 | F40: =IFERROR(GETPIVOTDATA("Sum of Revenue",Pivot!$B$27,"Months (Order_Date)",A40)+MAX($B$34:$B$45)*$F$46,NA()) -> 49476.67 | G40: =IFERROR(GETPIVOTDATA("Sum of Revenue",Pivot!$B$27,"Months (Order_Date)",A40),NA()) -> 42508.45
A41: AUG | B41: =GETPIVOTDATA("Sum of Revenue",Pivot!$B$44,"Months (Order_Date)",A41) -> 35726.1 | C41: =GETPIVOTDATA("Sum of Sales_Target",Pivot!$B$44,"Months (Order_Date)",A41) -> 34529 | D41: =IF($D$32,IFERROR(GETPIVOTDATA("Sum of Sales_Target",Pivot!$B$44,"Months (Order_Date)",A41),NA()),NA()) -> #N/A | E41: -3000 | F41: =IFERROR(GETPIVOTDATA("Sum of Revenue",Pivot!$B$27,"Months (Order_Date)",A41)+MAX($B$34:$B$45)*$F$46,NA()) -> 42694.32 | G41: =IFERROR(GETPIVOTDATA("Sum of Revenue",Pivot!$B$27,"Months (Order_Date)",A41),NA()) -> 35726.1
A42: SEP | B42: =GETPIVOTDATA("Sum of Revenue",Pivot!$B$44,"Months (Order_Date)",A42) -> 25604.9 | C42: =GETPIVOTDATA("Sum of Sales_Target",Pivot!$B$44,"Months (Order_Date)",A42) -> 29035 | D42: =IF($D$32,IFERROR(GETPIVOTDATA("Sum of Sales_Target",Pivot!$B$44,"Months (Order_Date)",A42),NA()),NA()) -> #N/A | E42: -3000 | F42: =IFERROR(GETPIVOTDATA("Sum of Revenue",Pivot!$B$27,"Months (Order_Date)",A42)+MAX($B$34:$B$45)*$F$46,NA()) -> 32573.12 | G42: =IFERROR(GETPIVOTDATA("Sum of Revenue",Pivot!$B$27,"Months (Order_Date)",A42),NA()) -> 25604.9
A43: OCT | B43: =GETPIVOTDATA("Sum of Revenue",Pivot!$B$44,"Months (Order_Date)",A43) -> 22430.05 | C43: =GETPIVOTDATA("Sum of Sales_Target",Pivot!$B$44,"Months (Order_Date)",A43) -> 19967 | D43: =IF($D$32,IFERROR(GETPIVOTDATA("Sum of Sales_Target",Pivot!$B$44,"Months (Order_Date)",A43),NA()),NA()) -> #N/A | E43: -3000 | F43: =IFERROR(GETPIVOTDATA("Sum of Revenue",Pivot!$B$27,"Months (Order_Date)",A43)+MAX($B$34:$B$45)*$F$46,NA()) -> 29398.27 | G43: =IFERROR(GETPIVOTDATA("Sum of Revenue",Pivot!$B$27,"Months (Order_Date)",A43),NA()) -> 22430.05
A44: NOV | B44: =GETPIVOTDATA("Sum of Revenue",Pivot!$B$44,"Months (Order_Date)",A44) -> 43618.95 | C44: =GETPIVOTDATA("Sum of Sales_Target",Pivot!$B$44,"Months (Order_Date)",A44) -> 44484 | D44: =IF($D$32,IFERROR(GETPIVOTDATA("Sum of Sales_Target",Pivot!$B$44,"Months (Order_Date)",A44),NA()),NA()) -> #N/A | E44: -3000 | F44: =IFERROR(GETPIVOTDATA("Sum of Revenue",Pivot!$B$27,"Months (Order_Date)",A44)+MAX($B$34:$B$45)*$F$46,NA()) -> 50587.17 | G44: =IFERROR(GETPIVOTDATA("Sum of Revenue",Pivot!$B$27,"Months (Order_Date)",A44),NA()) -> 43618.95
A45: DEC | B45: =GETPIVOTDATA("Sum of Revenue",Pivot!$B$44,"Months (Order_Date)",A45) -> 42847.85 | C45: =GETPIVOTDATA("Sum of Sales_Target",Pivot!$B$44,"Months (Order_Date)",A45) -> 38871 | D45: =IF($D$32,IFERROR(GETPIVOTDATA("Sum of Sales_Target",Pivot!$B$44,"Months (Order_Date)",A45),NA()),NA()) -> #N/A | E45: -3000 | F45: =IFERROR(GETPIVOTDATA("Sum of Revenue",Pivot!$B$27,"Months (Order_Date)",A45)+MAX($B$34:$B$45)*$F$46,NA()) -> 49816.07 | G45: =IFERROR(GETPIVOTDATA("Sum of Revenue",Pivot!$B$27,"Months (Order_Date)",A45),NA()) -> 42847.85
B46: =GETPIVOTDATA("Sum of Revenue",Pivot!$B$27) -> 401664.6 | C46: =GETPIVOTDATA("Sum of Sales_Target",Pivot!$B$27) -> 402280 | F46: 0.15
A50: Revenue by Category | B50: Revenue
A51: Accessories | B51: =GETPIVOTDATA("Revenue",Pivot!$B$60,"Category",A51) -> 89198.9 | C51: =B51/$B$56 -> 0.22207309
A52: Appliances | B52: =GETPIVOTDATA("Revenue",Pivot!$B$60,"Category",A52) -> 55714.75 | C52: =B52/$B$56 -> 0.13870963
A53: Furniture | B53: =GETPIVOTDATA("Revenue",Pivot!$B$60,"Category",A53) -> 64075.95 | C53: =B53/$B$56 -> 0.15952601
A54: Office Supplies | B54: =GETPIVOTDATA("Revenue",Pivot!$B$60,"Category",A54) -> 88250.5 | C54: =B54/$B$56 -> 0.21971192
A55: Technology | B55: =GETPIVOTDATA("Revenue",Pivot!$B$60,"Category",A55) -> 104424.5 | C55: =B55/$B$56 -> 0.25997935
B56: =SUM(B51:B55) -> 401664.6
A59: Revenue by Department
A60: Consumer | B60: =GETPIVOTDATA("Revenue",Pivot!$B$69,"Department",A60) -> 79123.5 | C60: =B60/$B$64 -> 0.19698898
A61: Corporate | B61: =GETPIVOTDATA("Revenue",Pivot!$B$69,"Department",A61) -> 85563.2 | C61: =B61/$B$64 -> 0.21302151
A62: Enterprise | B62: =GETPIVOTDATA("Revenue",Pivot!$B$69,"Department",A62) -> 75437.7 | C62: =B62/$B$64 -> 0.18781267
A63: Retail | B63: =GETPIVOTDATA("Revenue",Pivot!$B$69,"Department",A63) -> 161540.2 | C63: =B63/$B$64 -> 0.40217684
B64: =SUM(B60:B63) -> 401664.6 | C64: =SUM(B60:B63) -> 401664.6
A66: Expense Ratio % | C66: X | D66: Y
A67: =1-B67 -> 0.3555778 | B67: =GETPIVOTDATA("Average of Expense_Ratio_%",Pivot!$B$4) -> 0.6444222 | C67: =SIN(A68*2*PI()) -> 0.374477 | D67: =COS(B68*2*PI()) -> -0.9272362
A68: =A67+100%/12 -> 0.43891113 | B68: =100%-A68 -> 0.56108887 | C68: 0.5 | D68: 0.866
A70: Profit Margin % | C70: X | D70: Y
A71: =1-B71 -> 0.6444218 | B71: =GETPIVOTDATA("Average of Profit_Margin_%",Pivot!$B$4) -> 0.3555782 | C71: =SIN(A72*2*PI()) -> -0.99024826 | D71: =COS(B72*2*PI()) -> -0.13931399
A72: =A71+100%/12 -> 0.72775513 | B72: =100%-A72 -> 0.27224487 | C72: 0.5 | D72: 0.866
A76: Sources | B76: Revenue by Region | D76: Split Regions | F76: Revenue | G76: %
A77: Midwest | B77: =GETPIVOTDATA("Revenue",Pivot!$B$78,"Region",A77) -> 73286.7 | C77: =B77/$B$81 -> 0.18245745 | D77: Midwest | E77: =IF(ISNUMBER(MATCH(A77,Pivot!$B$88:$B$91,0)),C77,"") -> 0.18245745 | F77: =IF(ISNUMBER(MATCH(A77,Pivot!$B$88:$B$91,0)),B77,"") -> 73286.7 | G77: =IF(ISNUMBER(MATCH(A77,Pivot!$B$88:$B$91,0)),C77,"") -> 0.18245745
A78: Northeast | B78: =GETPIVOTDATA("Revenue",Pivot!$B$78,"Region",A78) -> 97010.2 | C78: =B78/$B$81 -> 0.24152041 | E78: =IF(ISNUMBER(MATCH(A77,Pivot!$B$88:$B$91,0)),NA(),C77) -> #N/A | F78: =IF(ISNUMBER(MATCH(A78,Pivot!$B$88:$B$91,0)),B78,"") -> 97010.2 | G78: =IF(ISNUMBER(MATCH(A78,Pivot!$B$88:$B$91,0)),C78,"") -> 0.24152041
A79: South | B79: =GETPIVOTDATA("Revenue",Pivot!$B$78,"Region",A79) -> 100937.25 | C79: =B79/$B$81 -> 0.25129735 | E79: =$B$83 -> 0.035 | F79: =IF(ISNUMBER(MATCH(A79,Pivot!$B$88:$B$91,0)),B79,"") -> 100937.25 | G79: =IF(ISNUMBER(MATCH(A79,Pivot!$B$88:$B$91,0)),C79,"") -> 0.25129735
A80: West | B80: =GETPIVOTDATA("Revenue",Pivot!$B$78,"Region",A80) -> 130430.45 | C80: =B80/$B$81 -> 0.32472478 | D80: Northeast | E80: =IF(ISNUMBER(MATCH(A78,Pivot!$B$88:$B$91,0)),C78,"") -> 0.24152041 | F80: =IF(ISNUMBER(MATCH(A80,Pivot!$B$88:$B$91,0)),B80,"") -> 130430.45 | G80: =IF(ISNUMBER(MATCH(A80,Pivot!$B$88:$B$91,0)),C80,"") -> 0.32472478
B81: =SUM(B77:B80) -> 401664.6 | E81: =IF(ISNUMBER(MATCH(A78,Pivot!$B$88:$B$91,0)),NA(),C78) -> #N/A
E82: =$B$83 -> 0.035
A83: Pading | B83: 0.035 | D83: South | E83: =IF(ISNUMBER(MATCH(A79,Pivot!$B$88:$B$91,0)),C79,"") -> 0.25129735
E84: =IF(ISNUMBER(MATCH(A79,Pivot!$B$88:$B$91,0)),NA(),C79) -> #N/A
E85: =$B$83 -> 0.035
D86: West | E86: =IF(ISNUMBER(MATCH(A80,Pivot!$B$88:$B$91,0)),C80,"") -> 0.32472478
E87: =IF(ISNUMBER(MATCH(A80,Pivot!$B$88:$B$91,0)),NA(),C80) -> #N/A
E88: =B83 -> 0.035
A92: Customer Type | C92: 2024 | D92: 2025
A93: New | B93: =GETPIVOTDATA("Revenue",Pivot!$B$104,"Customer_Type",A93) -> 154300.85 | C93: =GETPIVOTDATA("Revenue",Pivot!$B$96,"Years (Order_Date)",C92) -> 188339.45 | D93: =GETPIVOTDATA("Revenue",Pivot!$B$96,"Years (Order_Date)",D92) -> 213325.15
A94: Returning | B94: =GETPIVOTDATA("Revenue",Pivot!$B$104,"Customer_Type",A94) -> 247363.75 | C94: YoY Growth | D94: =(D93-C93)/C93 -> 0.13266313
C96: Positive | D96: =IF(D94>0,D94,"") -> 0.13266313
C97: Negative | D97: =IF(D94<0,D94,"")
A100: Revenue vs Expenses | B100: Revenue | C100: Expenses | D100: Cursor R | E100: Cursor E
A101: Jan | B101: =GETPIVOTDATA("Sum of Revenue",Pivot!$B$44,"Months (Order_Date)",A101) -> 31876.15 | C101: =GETPIVOTDATA("Sum of Expenses",Pivot!$B$44,"Months (Order_Date)",A101) -> 21232.49 | D101: =IFERROR(GETPIVOTDATA("Sum of Revenue",Pivot!$B$27,"Months (Order_Date)",A101),NA()) -> 31876.15 | E101: =IFERROR(GETPIVOTDATA("Sum of Expenses",Pivot!$B$27,"Months (Order_Date)",A101),NA()) -> 21232.49
A102: Feb | B102: =GETPIVOTDATA("Sum of Revenue",Pivot!$B$44,"Months (Order_Date)",A102) -> 46454.8 | C102: =GETPIVOTDATA("Sum of Expenses",Pivot!$B$44,"Months (Order_Date)",A102) -> 27219.7 | D102: =IFERROR(GETPIVOTDATA("Sum of Revenue",Pivot!$B$27,"Months (Order_Date)",A102),NA()) -> 46454.8 | E102: =IFERROR(GETPIVOTDATA("Sum of Expenses",Pivot!$B$27,"Months (Order_Date)",A102),NA()) -> 27219.7
A103: Mar | B103: =GETPIVOTDATA("Sum of Revenue",Pivot!$B$44,"Months (Order_Date)",A103) -> 25206.7 | C103: =GETPIVOTDATA("Sum of Expenses",Pivot!$B$44,"Months (Order_Date)",A103) -> 15475.44 | D103: =IFERROR(GETPIVOTDATA("Sum of Revenue",Pivot!$B$27,"Months (Order_Date)",A103),NA()) -> 25206.7 | E103: =IFERROR(GETPIVOTDATA("Sum of Expenses",Pivot!$B$27,"Months (Order_Date)",A103),NA()) -> 15475.44
A104: Apr | B104: =GETPIVOTDATA("Sum of Revenue",Pivot!$B$44,"Months (Order_Date)",A104) -> 32333.95 | C104: =GETPIVOTDATA("Sum of Expenses",Pivot!$B$44,"Months (Order_Date)",A104) -> 17947.33 | D104: =IFERROR(GETPIVOTDATA("Sum of Revenue",Pivot!$B$27,"Months (Order_Date)",A104),NA()) -> 32333.95 | E104: =IFERROR(GETPIVOTDATA("Sum of Expenses",Pivot!$B$27,"Months (Order_Date)",A104),NA()) -> 17947.33
A105: May | B105: =GETPIVOTDATA("Sum of Revenue",Pivot!$B$44,"Months (Order_Date)",A105) -> 29518.1 | C105: =GETPIVOTDATA("Sum of Expenses",Pivot!$B$44,"Months (Order_Date)",A105) -> 19789.03 | D105: =IFERROR(GETPIVOTDATA("Sum of Revenue",Pivot!$B$27,"Months (Order_Date)",A105),NA()) -> 29518.1 | E105: =IFERROR(GETPIVOTDATA("Sum of Expenses",Pivot!$B$27,"Months (Order_Date)",A105),NA()) -> 19789.03
A106: Jun | B106: =GETPIVOTDATA("Sum of Revenue",Pivot!$B$44,"Months (Order_Date)",A106) -> 23538.6 | C106: =GETPIVOTDATA("Sum of Expenses",Pivot!$B$44,"Months (Order_Date)",A106) -> 13803.99 | D106: =IFERROR(GETPIVOTDATA("Sum of Revenue",Pivot!$B$27,"Months (Order_Date)",A106),NA()) -> 23538.6 | E106: =IFERROR(GETPIVOTDATA("Sum of Expenses",Pivot!$B$27,"Months (Order_Date)",A106),NA()) -> 13803.99
A107: Jul | B107: =GETPIVOTDATA("Sum of Revenue",Pivot!$B$44,"Months (Order_Date)",A107) -> 42508.45 | C107: =GETPIVOTDATA("Sum of Expenses",Pivot!$B$44,"Months (Order_Date)",A107) -> 27909.07 | D107: =IFERROR(GETPIVOTDATA("Sum of Revenue",Pivot!$B$27,"Months (Order_Date)",A107),NA()) -> 42508.45 | E107: =IFERROR(GETPIVOTDATA("Sum of Expenses",Pivot!$B$27,"Months (Order_Date)",A107),NA()) -> 27909.07
A108: Aug | B108: =GETPIVOTDATA("Sum of Revenue",Pivot!$B$44,"Months (Order_Date)",A108) -> 35726.1 | C108: =GETPIVOTDATA("Sum of Expenses",Pivot!$B$44,"Months (Order_Date)",A108) -> 24265.98 | D108: =IFERROR(GETPIVOTDATA("Sum of Revenue",Pivot!$B$27,"Months (Order_Date)",A108),NA()) -> 35726.1 | E108: =IFERROR(GETPIVOTDATA("Sum of Expenses",Pivot!$B$27,"Months (Order_Date)",A108),NA()) -> 24265.98
A109: Sep | B109: =GETPIVOTDATA("Sum of Revenue",Pivot!$B$44,"Months (Order_Date)",A109) -> 25604.9 | C109: =GETPIVOTDATA("Sum of Expenses",Pivot!$B$44,"Months (Order_Date)",A109) -> 14316.28 | D109: =IFERROR(GETPIVOTDATA("Sum of Revenue",Pivot!$B$27,"Months (Order_Date)",A109),NA()) -> 25604.9 | E109: =IFERROR(GETPIVOTDATA("Sum of Expenses",Pivot!$B$27,"Months (Order_Date)",A109),NA()) -> 14316.28
A110: Oct | B110: =GETPIVOTDATA("Sum of Revenue",Pivot!$B$44,"Months (Order_Date)",A110) -> 22430.05 | C110: =GETPIVOTDATA("Sum of Expenses",Pivot!$B$44,"Months (Order_Date)",A110) -> 15784.97 | D110: =IFERROR(GETPIVOTDATA("Sum of Revenue",Pivot!$B$27,"Months (Order_Date)",A110),NA()) -> 22430.05 | E110: =IFERROR(GETPIVOTDATA("Sum of Expenses",Pivot!$B$27,"Months (Order_Date)",A110),NA()) -> 15784.97
A111: Nov | B111: =GETPIVOTDATA("Sum of Revenue",Pivot!$B$44,"Months (Order_Date)",A111) -> 43618.95 | C111: =GETPIVOTDATA("Sum of Expenses",Pivot!$B$44,"Months (Order_Date)",A111) -> 28440.33 | D111: =IFERROR(GETPIVOTDATA("Sum of Revenue",Pivot!$B$27,"Months (Order_Date)",A111),NA()) -> 43618.95 | E111: =IFERROR(GETPIVOTDATA("Sum of Expenses",Pivot!$B$27,"Months (Order_Date)",A111),NA()) -> 28440.33
A112: Dec | B112: =GETPIVOTDATA("Sum of Revenue",Pivot!$B$44,"Months (Order_Date)",A112) -> 42847.85 | C112: =GETPIVOTDATA("Sum of Expenses",Pivot!$B$44,"Months (Order_Date)",A112) -> 31312.2 | D112: =IFERROR(GETPIVOTDATA("Sum of Revenue",Pivot!$B$27,"Months (Order_Date)",A112),NA()) -> 42847.85 | E112: =IFERROR(GETPIVOTDATA("Sum of Expenses",Pivot!$B$27,"Months (Order_Date)",A112),NA()) -> 31312.2
B113: =SUMIF(D101:D112,">0",B101:B112) -> 401664.6 | C113: =SUMIF(E101:E112,">0",C101:C112) -> 257496.81
A117: Revene by Category
A118: Accessories | B118: =GETPIVOTDATA("Revenue",Pivot!$B$110,"Category",A118) -> 89198.9 | D118: {=_xlfn._xlws.SORT(A118:B122,2,-1)} -> Technology | E118: 104424.5
A119: Appliances | B119: =GETPIVOTDATA("Revenue",Pivot!$B$110,"Category",A119) -> 55714.75 | D119: Accessories | E119: 89198.9
A120: Furniture | B120: =GETPIVOTDATA("Revenue",Pivot!$B$110,"Category",A120) -> 64075.95 | D120: Office Supplies | E120: 88250.5
A121: Office Supplies | B121: =GETPIVOTDATA("Revenue",Pivot!$B$110,"Category",A121) -> 88250.5 | D121: Furniture | E121: 64075.95
A122: Technology | B122: =GETPIVOTDATA("Revenue",Pivot!$B$110,"Category",A122) -> 104424.5 | D122: Appliances | E122: 55714.75
B123: =SUM(B118:B122) -> 401664.6
A126: Monthly QTY Performance | B126: QTY | C126: indent | D126: Marker
A127: Jan | B127: =GETPIVOTDATA("Sum of Quantity",Pivot!$B$44,"Months (Order_Date)",A127) -> 172 | C127: =IFERROR(GETPIVOTDATA("Sum of Quantity",Pivot!$B$27,"Months (Order_Date)",A127),NA()) -> 172 | D127: =IFERROR(GETPIVOTDATA("Sum of Quantity",Pivot!$B$27,"Months (Order_Date)",A127),NA()) -> 172
...

Sheet Dashboard

Sheet Profitability

Sheet Operations

Sheet Dataset
B6: Order_ID | C6: Order_Date | D6: City | E6: Region | F6: Category | G6: Sub_Category | H6: Department | I6: Customer_Type | J6: Order_Priority | K6: Quantity | L6: Unit_Price | M6: Discount_% | N6: Gross_Sales | O6: Revenue | P6: Expenses | Q6: Profit | R6: Profit_Margin_% | S6: Expense_Ratio_% | T6: Sales_Target | U6: Target_Achievement_% | V6: Return_Qty | W6: Return_Rate_%
B7: ORD-00001 | C7: 45550 | D7: Phoenix | E7: West | F7: Accessories | G7: Bags | H7: Corporate | I7: Returning | J7: Standard | K7: 4 | L7: 300 | M7: 0.03 | N7: 1200 | O7: 1164 | P7: 601.82 | Q7: 562.18 | R7: 0.483 | S7: 0.517 | T7: 876 | U7: 1.7321 | V7: 1 | W7: 0.25
B8: ORD-00002 | C8: 45409 | D8: Los Angeles | E8: West | F8: Technology | G8: Kitchen | H8: Retail | I8: Returning | J8: Standard | K8: 5 | L8: 25 | M8: 0.15 | N8: 125 | O8: 106.25 | P8: 71.94 | Q8: 34.31 | R8: 0.3229 | S8: 0.6771 | T8: 63 | U8: 0.1124 | V8: 0 | W8: 0
B9: ORD-00003 | C9: 45999 | D9: New York | E9: Northeast | F9: Technology | G9: Chairs | H9: Retail | I9: Returning | J9: Standard | K9: 4 | L9: 200 | M9: 0.08 | N9: 800 | O9: 736 | P9: 548.02 | Q9: 187.98 | R9: 0.2554 | S9: 0.7446 | T9: 587 | U9: 0.6815 | V9: 0 | W9: 0
B10: ORD-00004 | C10: 45542 | D10: Los Angeles | E10: West | F10: Office Supplies | G10: Bags | H10: Corporate | I10: Returning | J10: Standard | K10: 5 | L10: 150 | M10: 0 | N10: 750 | O10: 750 | P10: 431.08 | Q10: 318.92 | R10: 0.4252 | S10: 0.5748 | T10: 907 | U10: 1.0302 | V10: 0 | W10: 0
B11: ORD-00005 | C11: 45913 | D11: Los Angeles | E11: West | F11: Office Supplies | G11: Laptops | H11: Corporate | I11: Returning | J11: Express | K11: 5 | L11: 40 | M11: 0 | N11: 200 | O11: 200 | P11: 105.1 | Q11: 94.9 | R11: 0.4745 | S11: 0.5255 | T11: 205 | U11: 0.2747 | V11: 1 | W11: 0.2
B12: ORD-00006 | C12: 45972 | D12: Miami | E12: South | F12: Appliances | G12: Kitchen | H12: Retail | I12: New | J12: Standard | K12: 5 | L12: 750 | M12: 0.1 | N12: 3750 | O12: 3375 | P12: 2508.73 | Q12: 866.27 | R12: 0.2567 | S12: 0.7433 | T12: 2279 | U12: 3.5156 | V12: 1 | W12: 0.2
B13: ORD-00007 | C13: 45422 | D13: Houston | E13: South | F13: Furniture | G13: Bags | H13: Consumer | I13: Returning | J13: Standard | K13: 2 | L13: 500 | M13: 0.05 | N13: 1000 | O13: 950 | P13: 590.03 | Q13: 359.97 | R13: 0.3789 | S13: 0.6211 | T13: 1032 | U13: 1.2056 | V13: 0 | W13: 0
B14: ORD-00008 | C14: 45361 | D14: Miami | E14: South | F14: Appliances | G14: Phones | H14: Consumer | I14: New | J14: Standard | K14: 6 | L14: 60 | M14: 0.05 | N14: 360 | O14: 342 | P14: 226.89 | Q14: 115.11 | R14: 0.3366 | S14: 0.6634 | T14: 372 | U14: 0.4275 | V14: 1 | W14: 0.1667
B15: ORD-00009 | C15: 45521 | D15: New York | E15: Northeast | F15: Office Supplies | G15: Laptops | H15: Enterprise | I15: New | J15: Standard | K15: 3 | L15: 60 | M15: 0.1 | N15: 180 | O15: 162 | P15: 107.92 | Q15: 54.08 | R15: 0.3338 | S15: 0.6662 | T15: 173 | U15: 0.2225 | V15: 0 | W15: 0
B16: ORD-00010 | C16: 45882 | D16: Phoenix | E16: West | F16: Office Supplies | G16: Phones | H16: Enterprise | I16: Returning | J16: Express | K16: 4 | L16: 100 | M16: 0.15 | N16: 400 | O16: 340 | P16: 235.85 | Q16: 104.15 | R16: 0.3063 | S16: 0.6937 | T16: 365 | U16: 0.467 | V16: 0 | W16: 0
B17: ORD-00011 | C17: 45848 | D17: Los Angeles | E17: West | F17: Accessories | G17: Laptops | H17: Retail | I17: Returning | J17: Standard | K17: 5 | L17: 750 | M17: 0 | N17: 3750 | O17: 3750 | P17: 2617.46 | Q17: 1132.54 | R17: 0.302 | S17: 0.698 | T17: 1731 | U17: 5.5804 | V17: 0 | W17: 0
B18: ORD-00012 | C18: 45786 | D18: Miami | E18: South | F18: Office Supplies | G18: Kitchen | H18: Consumer | I18: New | J18: Standard | K18: 1 | L18: 25 | M18: 0.08 | N18: 25 | O18: 23 | P18: 15.33 | Q18: 7.67 | R18: 0.3335 | S18: 0.6665 | T18: 25 | U18: 0.0337 | V18: 0 | W18: 0
... B506: ORD-00500 | C506: 45849 | D506: New York | E506: Northeast | F506: Accessories | G506: Kitchen | H506: Corporate | I506: Returning | J506: Standard | K506: 1 | L506: 60 | M506: 0 | N506: 60 | O506: 60 | P506: 43.39 | Q506: 16.61 | R506: 0.2768 | S506: 0.7232 | T506: 672 | U506: 0.0893 | V506: 0 | W506: 0

Sheet Insights

Sheet Feuil1
